tfi/__init__.py
tfi/as_tensor.py
tfi/data.py
tfi/saved_model.py
tfi-0.4.dist-info/DESCRIPTION.rst
tfi-0.4.dist-info/LICENSE.txt
tfi-0.4.dist-info/METADATA
tfi-0.4.dist-info/RECORD
tfi-0.4.dist-info/WHEEL
tfi-0.4.dist-info/metadata.json
tfi-0.4.dist-info/top_level.txt
