Metadata-Version: 2.0
Name: tfi
Version: 0.4
Summary: Use any TensorFlow model in a single line of code
Home-page: https://github.com/ajbouh/tfi
Author: Adam Bouhenguel
Author-email: adam@bouhenguel.com
License: MIT
Keywords: tensorflow,savedmodel,boilerplate
Platform: UNKNOWN
Classifier: Development Status :: 3 - Alpha
Classifier: Intended Audience :: Developers
Classifier: Natural Language :: English
Classifier: License :: OSI Approved :: MIT License
Classifier: Operating System :: OS Independent
Classifier: Programming Language :: Python
Classifier: Programming Language :: Python :: 3
Classifier: Programming Language :: Python :: Implementation :: CPython
Classifier: Topic :: Software Development :: Libraries :: Python Modules
Requires-Dist: tensorflow (>=1.3)
